pycades/__init__.py
pycades/_pycades.so
pycades/pycades.py
pycades/config-123456/cprocsp/__init__.py
pycades/config-123456/cprocsp/config64.ini
pycades/config-123456/cprocsp/license.ini
pycades/config64/cprocsp/__init__.py
pycades/config64/cprocsp/config64.ini
pycades/config64/cprocsp/license.ini
pycades/cprocsp/lib/amd64/__init__.py
pycades/cprocsp/lib/amd64/libades-core.so
pycades/cprocsp/lib/amd64/libades-core.so.2
pycades/cprocsp/lib/amd64/libades-core.so.2.0.0
pycades/cprocsp/lib/amd64/libcades.so
pycades/cprocsp/lib/amd64/libcades.so.2
pycades/cprocsp/lib/amd64/libcades.so.2.0.0
pycades/cprocsp/lib/amd64/libcapi10.so
pycades/cprocsp/lib/amd64/libcapi10.so.4
pycades/cprocsp/lib/amd64/libcapi10.so.4.0.5
pycades/cprocsp/lib/amd64/libcapi20.so
pycades/cprocsp/lib/amd64/libcapi20.so.4
pycades/cprocsp/lib/amd64/libcapi20.so.4.0.5
pycades/cprocsp/lib/amd64/libcpalloc.so
pycades/cprocsp/lib/amd64/libcpalloc.so.0
pycades/cprocsp/lib/amd64/libcpalloc.so.0.0.0
pycades/cprocsp/lib/amd64/libcpcurl.a
pycades/cprocsp/lib/amd64/libcpcurl.so
pycades/cprocsp/lib/amd64/libcpcurl.so.4
pycades/cprocsp/lib/amd64/libcpcurl.so.4.5.0
pycades/cprocsp/lib/amd64/libcpext.so
pycades/cprocsp/lib/amd64/libcpext.so.4
pycades/cprocsp/lib/amd64/libcpext.so.4.0.5
pycades/cprocsp/lib/amd64/libcppcades.so
pycades/cprocsp/lib/amd64/libcppcades.so.2
pycades/cprocsp/lib/amd64/libcppcades.so.2.0.0
pycades/cprocsp/lib/amd64/libcpui.so
pycades/cprocsp/lib/amd64/libcpui.so.4
pycades/cprocsp/lib/amd64/libcpui.so.4.0.5
pycades/cprocsp/lib/amd64/libcsp.so
pycades/cprocsp/lib/amd64/libcsp.so.4
pycades/cprocsp/lib/amd64/libcsp.so.4.0.5
pycades/cprocsp/lib/amd64/libenroll.so
pycades/cprocsp/lib/amd64/libenroll.so.4
pycades/cprocsp/lib/amd64/libenroll.so.4.0.5
pycades/cprocsp/lib/amd64/libocsp.so
pycades/cprocsp/lib/amd64/libocsp.so.2
pycades/cprocsp/lib/amd64/libocsp.so.2.0.0
pycades/cprocsp/lib/amd64/libocspcli.so
pycades/cprocsp/lib/amd64/libocspcli.so.2
pycades/cprocsp/lib/amd64/libocspcli.so.2.0.0
pycades-1.1.4.dist-info/METADATA
pycades-1.1.4.dist-info/WHEEL
pycades-1.1.4.dist-info/top_level.txt
pycades-1.1.4.dist-info/RECORD
