Metadata-Version: 2.1
Name: pycades
Version: 1.1.4
Summary: Расширение Pycades предоставляет программный интерфейс, аналогичный КриптоПро
Author: Kirill Ogleznev
Author-email: Kirill Ogleznev <kirill24680@gmail.com>
Project-URL: homepage, https://docs.cryptopro.ru/cades/pycades
Project-URL: documentation, https://docs.cryptopro.ru/cades/pycades
Project-URL: source, https://github.com/KirillOgleznev/pycades
